src/__init__.py
src/__main__.py
src/main.py
src/version.py
pdf_toc-1.1.3.dist-info/LICENSE
pdf_toc-1.1.3.dist-info/METADATA
pdf_toc-1.1.3.dist-info/WHEEL
pdf_toc-1.1.3.dist-info/entry_points.txt
pdf_toc-1.1.3.dist-info/top_level.txt
pdf_toc-1.1.3.dist-info/RECORD
