Metadata-Version: 2.1
Name: pdf-toc
Version: 1.1.3
Summary: a pdf ToC CLI tool
Home-page: https://github.com/HareInWeed/pdf-toc
Author: HareInWeed
Author-email: zjnvv@163.com
License: UNKNOWN
Project-URL: Bug Tracker, https://github.com/HareInWeed/pdf-toc/issues
Project-URL: Documentation, https://github.com/HareInWeed/pdf-toc
Project-URL: Source Code, https://github.com/HareInWeed/pdf-toc
Platform: UNKNOWN
Classifier: Programming Language :: Python :: 3
Classifier: License :: OSI Approved :: MIT License
Classifier: Operating System :: OS Independent
Requires-Python: >=3.6
Requires-Dist: PyMuPDF
